[
  {
    "Id": "CHALLENGES_DAILY_TRIVIA_TAB",
    "X": 0.4415761,
    "Y": 0.13542926,
    "W": 0.11616847,
    "H": 0.04594922,
    "Text": "DAILY TRIVIA"
  },
  {
    "Id": "CHALLENGES_DAILY_START_BUTTON",
    "X": 0.74654657,
    "Y": 0.8130342,
    "W": 0.067867875,
    "H": 0.05448717,
    "Text": "START"
  },
  {
    "Id": "CHALLENGES_DAILY_TRIVIA_ANSWER_DYN",
    "X": 0.684,
    "Y": 0.403,
    "W": 0.228,
    "H": 0.102,
    "XOffset": 1.0,
    "YOffset": 0.126
  },
  {
    "Id": "CHALLENGES_DAILY_TRIVIA_QUESTION",
    "X": 0.102,
    "Y": 0.49,
    "W": 0.485,
    "H": 0.175
  },
  {
    "Id": "CHALLENGES_DAILY_TRIVIA_CLOSE_BUTTON",
    "X": 0.466,
    "Y": 0.743,
    "W": 0.073,
    "H": 0.073,
    "Text": "CLOSE"
  },
  {
    "Id": "CHALLENGES_DAILY_TRIVIA_QUESTION_STATUS",
    "X": 0.245,
    "Y": 0.413,
    "W": 0.042,
    "H": 0.044
  },
  {
    "Id": "CHALLENGES_DAILY_TRIVIA_BASIC_REWARD",
    "X": 0.142,
    "Y": 0.6888889,
    "W": 0.0890625,
    "H": 0.028703704,
    "Text": "BASIC REWARD"
  },
  {
    "Id": "CHALLENGES_DAILY_NOTIFICATION_CHALLLENGES",
    "X": 0.796875,
    "Y": 0.7777778,
    "W": 0.12031251,
    "H": 0.047222197,
    "Text": "CHALLENGES"
  },
  {
    "Id": "CHALLENGES_DAILY_NOTIFICATION_CHALLLENGES_OK",
    "X": 0.840625,
    "Y": 0.8712963,
    "W": 0.034895837,
    "H": 0.0462963,
    "Text": "OK"
  }
]